{"nm":"Frame 313","ddd":0,"h":155,"w":174,"meta":{"g":"LottieFiles Figma v64"},"layers":[{"ty":4,"nm":"Rectangle 105","sr":1,"st":0,"op":61,"ip":0,"hd":false,"ddd":0,"bm":0,"hasMask":false,"ao":0,"ks":{"a":{"a":1,"k":[{"o":{"x":0.33,"y":1},"i":{"x":0.68,"y":1},"s":[19.5,19],"t":0},{"s":[19.5,19],"t":60}]},"s":{"a":1,"k":[{"o":{"x":0.33,"y":1},"i":{"x":0.68,"y":1},"s":[100,100],"t":0},{"s":[100,100],"t":60}]},"sk":{"a":0,"k":0},"p":{"a":1,"k":[{"o":{"x":0.33,"y":1},"i":{"x":0.68,"y":1},"s":[88.5,69],"t":0},{"s":[101.5,68],"t":60}]},"r":{"a":1,"k":[{"o":{"x":0.33,"y":1},"i":{"x":0.68,"y":1},"s":[0],"t":0},{"s":[0],"t":60}]},"sa":{"a":0,"k":0},"o":{"a":1,"k":[{"o":{"x":0.33,"y":1},"i":{"x":0.68,"y":1},"s":[100],"t":0},{"s":[100],"t":60}]}},"shapes":[{"ty":"sh","bm":0,"hd":false,"nm":"","d":1,"ks":{"a":1,"k":[{"o":{"x":0.33,"y":1},"i":{"x":0.68,"y":1},"s":[{"c":true,"i":[[0,0],[0,0],[0,0],[0,0]],"o":[[0,0],[0,0],[0,0],[0,0]],"v":[[39,0],[39,38],[0,38],[0,0]]}],"t":0},{"s":[{"c":true,"i":[[0,0],[0,0],[0,0],[0,0]],"o":[[0,0],[0,0],[0,0],[0,0]],"v":[[39,0],[39,38],[0,38],[0,0]]}],"t":60}]}},{"ty":"fl","bm":0,"hd":false,"nm":"","c":{"a":1,"k":[{"o":{"x":0.33,"y":1},"i":{"x":0.68,"y":1},"s":[1,0.0542,0.0542],"t":0},{"s":[1,0.0542,0.0542],"t":60}]},"r":1,"o":{"a":1,"k":[{"o":{"x":0.33,"y":1},"i":{"x":0.68,"y":1},"s":[100],"t":0},{"s":[100],"t":60}]}}],"ind":1}],"v":"5.7.0","fr":60,"op":60,"ip":0,"assets":[]}